pypi_analyser/__init__.py
pypi_analyser/pypi_analyser.py
pypi_analyser-1.0.0.dist-info/LICENSE
pypi_analyser-1.0.0.dist-info/METADATA
pypi_analyser-1.0.0.dist-info/WHEEL
pypi_analyser-1.0.0.dist-info/top_level.txt
pypi_analyser-1.0.0.dist-info/RECORD
